andy_mpc_py-0.4.0.dist-info/METADATA
andy_mpc_py-0.4.0.dist-info/WHEEL
mpc_py/__init__.py
mpc_py/mpc_py.abi3.so
andy_mpc_py-0.4.0.dist-info/RECORD
