Metadata-Version: 2.4
Name: andy-mpc-py
Version: 0.4.0
Classifier: Programming Language :: Python
Classifier: Programming Language :: Rust
Classifier: Framework :: AsyncIO
Summary: Minimal hub-and-spoke message pipe for arbitrary Python objects (pickle over Tokio)
Author: You
License: MIT
Requires-Python: >=3.9
